ctu_mars_control_unit-0.1.1.dist-info/METADATA
ctu_mars_control_unit-0.1.1.dist-info/WHEEL
ctu_mars_control_unit-0.1.1.dist-info/licenses/LICENSE
ctu_mars_control_unit/__init__.py
ctu_mars_control_unit/mars_control_unit.py
ctu_mars_control_unit-0.1.1.dist-info/RECORD
