Metadata-Version: 2.1
Name: ctu_mars_control_unit
Version: 0.1.1
Summary: MARS control unit that is used to control robots at CIIRC/CTU
Author-Email: Vladimir Petrik <vladimir.petrik@cvut.cz>
License: BSD 3-Clause
Requires-Python: >=3.8
Requires-Dist: pyserial>=3.5
Requires-Dist: numpy>=1.24.4
